{
  "minimal-style@@h1-size": "1.5em",
  "minimal-style@@file-header-visibility": "minimal-tab-title-hidden",
  "shimmering-focus@@bg-hue-light": 230,
  "shimmering-focus@@sidenote-callout-width": 18,
  "modular-css-layout-wv@@wide-dataview-global": false,
  "modular-css-layout-wv@@wide-table-global": false,
  "modular-css-layout-wv@@wide-callout-global": false,
  "modular-css-layout-wv@@wide-backlinks-global": false,
  "modular-css-layout-mc@@mcc-img-snw-display": "none",
  "sanctum@@light-mode-contrast-mode": "sanctum-contrast-light",
  "sanctum@@dark-mode-contrast-mode": "sanctum-contrast-dark",
  "sanctum@@color-accent-rgb-l": "165, 119, 218",
  "sanctum@@color-accent-rgb-d": "165, 119, 218",
  "sanctum@@wrap-kanban-lanes": false,
  "sanctum@@callout-border-width": 5,
  "modular-css-layout-mc@@callout-gap": "2rem",
  "modular-css-layout-mc@@float-callout-snw-display": "inline-block",
  "modular-css-layout-mc@@list-min-width": 200,
  "sanctum@@active-line-accent": "var(--background-hover)",
  "sanctum@@blockquote-border-thickness": 2.5,
  "sanctum@@blockquote-marker": false,
  "sanctum@@blockquote-border": false,
  "sanctum@@blockquote-font-style": "normal",
  "modular-css-layout-mc@@float-callout-top-margin": "2.5em",
  "sanctum@@table-cell-border": false,
  "sanctum@@table-row-border": false,
  "sanctum@@table-column-border": false,
  "sanctum@@table-alternate-row": true,
  "sanctum@@table-alternate-column": false,
  "sanctum@@table-hover-row": false,
  "sanctum@@table-sticky-headers": true,
  "sanctum@@table-tabular-figures": false,
  "sanctum@@table-nums": false,
  "sanctum@@nav-folder-indicators": false,
  "sanctum@@colorful-active-nav": false,
  "sanctum@@code-border": false,
  "sanctum@@clean-embeds": false,
  "modular-css-layout-mc@@callout-nowrap-min-width": 150,
  "sanctum@@aside-counter": false,
  "sanctum@@aside-border": false,
  "minimal-style@@h1-l": true,
  "minimal-style@@h2-l": true,
  "minimal-style@@h3-l": true,
  "minimal-style@@h4-l": true,
  "minimal-style@@h5-l": true,
  "minimal-style@@h6-l": true,
  "minimal-style@@tag-border-width": "2px",
  "minimal-style@@window-title-off": false,
  "minimal-style@@titlebar-text-color-focused@@dark": "#19A660",
  "minimal-style@@titlebar-text-color@@dark": "#309FBB",
  "minimal-style@@titlebar-text-weight": 500,
  "minimal-advanced@@styled-scrollbars": false,
  "minimal-style@@sidebar-lines-off": false,
  "minimal-style@@trim-cols": true,
  "minimal-style@@callouts-style": "callouts-default",
  "minimal-style@@callout-blend-mode": "var(--highlight-mix-blend-mode)",
  "minimal-style@@blockquote-border-thickness": 3,
  "minimal-style@@max-col-width": "15em",
  "sanctum@@table-single-rows": false,
  "minimal-style@@col-lines": true,
  "minimal-style@@row-alt": true,
  "minimal-style@@table-nowrap": false,
  "minimal-style@@row-lines": false,
  "minimal-style@@table-tabular": false,
  "minimal-style@@table-numbers": false,
  "minimal-style@@row-hover": true,
  "sanctum@@tag-border-width": "0px",
  "sanctum@@tag-decoration": "none",
  "blue-topaz-theme@@table-format-options": "no-wrapped-table-cell",
  "blue-topaz-theme@@full-width-table": false,
  "blue-topaz-theme@@table-style-options": "table-style-three",
  "blue-topaz-theme@@remove-table-transition": false,
  "blue-topaz-theme@@dvtable-style-options": "no-wrapped-dvtable-cell",
  "minimal-style@@col-alt": false,
  "minimal-style@@table-lines": false,
  "minimal-style@@maximize-tables-off": "maximize-tables-off",
  "minimal-style@@minimal-unstyled-tags": false,
  "sanctum@@code-lines": false,
  "sanctum@@code-label": false,
  "modular-css-layout-mc@@callout-min-width": 150,
  "modular-css-layout-mc@@callout-margin": "5px",
  "modular-css-layout-mc@@float-medium-width": 400,
  "modular-css-layout-mc@@float-small-width": 300,
  "modular-css-layout-mc@@float-large-width": 600,
  "sanctum@@h5-line": false,
  "sanctum@@h3-style": "normal",
  "sanctum@@h5-style": "normal",
  "sanctum@@h6-style": "normal",
  "sanctum@@h4-style": "normal",
  "sanctum@@h2-line": false,
  "sanctum@@h3-line": false,
  "buttons-styles@@button-box-shadow@@dark": "#F5F6F800",
  "buttons-styles@@button-border@@dark": "#5E4778",
  "modular-css-layout-wv@@is-adj-rll": true
}